retroapi/__init__.py
retroapi/convert_name2smiles.py
retroapi/retro_api.py
tests/__init__.py
tests/test_name2smiles.py
tests/test_retro_api.py
retroapi-0.8.10.dist-info/METADATA
retroapi-0.8.10.dist-info/WHEEL
retroapi-0.8.10.dist-info/top_level.txt
retroapi-0.8.10.dist-info/RECORD
