Metadata-Version: 2.1
Name: retroapi
Version: 0.8.10
Summary: A wrap retroapi package for retrosynthesis routes and exploring reaction conditions
Home-page: https://github.com/bruceunx/retrosynthesis
Author: Bruceunx
Author-email: bruceunx@gmail.com
License: MIT License
Project-URL: Source, https://github.com/bruceunx/retrosynthesis
Classifier: Intended Audience :: Science/Research
Classifier: Intended Audience :: Healthcare Industry
Classifier: Intended Audience :: Developers
Classifier: Topic :: Scientific/Engineering
Classifier: Topic :: Scientific/Engineering :: Bio-Informatics
Classifier: Topic :: Scientific/Engineering :: Chemistry
Classifier: Topic :: Software Development :: Libraries :: Python Modules
Classifier: Topic :: Internet
Classifier: License :: OSI Approved :: MIT License
Classifier: Programming Language :: Python :: 3
Classifier: Programming Language :: Python :: 3.8
Classifier: Programming Language :: Python :: 3.9
Classifier: Programming Language :: Python :: 3.10
Classifier: Programming Language :: Python :: 3.11
Classifier: Programming Language :: Python :: 3.12
Requires-Python: >=3.8,<3.13
Requires-Dist: requests
Requires-Dist: aiohttp
